vera_2_agentic_ai/__init__.py
vera_2_agentic_ai/__main__.py
vera_2_agentic_ai/app.py
vera_2_agentic_ai-0.4.2.dist-info/LICENSE
vera_2_agentic_ai-0.4.2.dist-info/METADATA
vera_2_agentic_ai-0.4.2.dist-info/WHEEL
vera_2_agentic_ai-0.4.2.dist-info/entry_points.txt
vera_2_agentic_ai-0.4.2.dist-info/RECORD
