Metadata-Version: 2.3
Name: vera-2-agentic-ai
Version: 0.4.2
Summary: 
Author: Praveen Govindaraj
Author-email: 38414524+Praveengovianalytics@users.noreply.github.com
Requires-Python: >=3.11,<4.0
Classifier: Programming Language :: Python :: 3
Classifier: Programming Language :: Python :: 3.11
Classifier: Programming Language :: Python :: 3.12
Classifier: Programming Language :: Python :: 3.13
Requires-Dist: aiohttp (>=3.12.11,<4.0.0)
Requires-Dist: gradio (>=5.33.0,<6.0.0)
Requires-Dist: langgraph (>=0.4.8,<0.5.0)
Requires-Dist: langmem (>=0.0.27,<0.0.28)
Requires-Dist: openai (>=1.84.0,<2.0.0)
Requires-Dist: openai-agents (>=0.0.17,<0.0.18)
Requires-Dist: python-dotenv (>=1.1.0,<2.0.0)
